mymetal/__init__.py
mymetal/aa.csv
mymetal/classes.py
mymetal/encode.py
mymetal/iof.py
mymetal/jenks.py
mymetal/load_dicts.py
mymetal/mbp.py
mymetal/parser.py
mymetal/ModelPersistency/ANNmodelMono.h5
mymetal/ModelPersistency/ANNmodelMono.json
mymetal/ModelPersistency/ANNmodelMulti.h5
mymetal/ModelPersistency/ANNmodelMulti.json
mymetal/ModelPersistency/ANNmodelT2CA.h5
mymetal/ModelPersistency/ANNmodelT2CA.json
mymetal/ModelPersistency/ANNmodelT2CO.h5
mymetal/ModelPersistency/ANNmodelT2CO.json
mymetal/ModelPersistency/ANNmodelT2CU.h5
mymetal/ModelPersistency/ANNmodelT2CU.json
mymetal/ModelPersistency/ANNmodelT2FE.h5
mymetal/ModelPersistency/ANNmodelT2FE.json
mymetal/ModelPersistency/ANNmodelT2K.h5
mymetal/ModelPersistency/ANNmodelT2K.json
mymetal/ModelPersistency/ANNmodelT2MG.h5
mymetal/ModelPersistency/ANNmodelT2MG.json
mymetal/ModelPersistency/ANNmodelT2MN.h5
mymetal/ModelPersistency/ANNmodelT2MN.json
mymetal/ModelPersistency/ANNmodelT2NA.h5
mymetal/ModelPersistency/ANNmodelT2NA.json
mymetal/ModelPersistency/ANNmodelT2NI.h5
mymetal/ModelPersistency/ANNmodelT2NI.json
mymetal/ModelPersistency/ANNmodelT2ZN.h5
mymetal/ModelPersistency/ANNmodelT2ZN.json
mymetal/kmer_counts/5mer_5Acounts.txt
mymetal/kmer_counts/5mer_5AcountsCA.txt
mymetal/kmer_counts/5mer_5AcountsCO.txt
mymetal/kmer_counts/5mer_5AcountsCU.txt
mymetal/kmer_counts/5mer_5AcountsFE.txt
mymetal/kmer_counts/5mer_5AcountsK.txt
mymetal/kmer_counts/5mer_5AcountsMG.txt
mymetal/kmer_counts/5mer_5AcountsMN.txt
mymetal/kmer_counts/5mer_5AcountsNA.txt
mymetal/kmer_counts/5mer_5AcountsNI.txt
mymetal/kmer_counts/5mer_5AcountsZN.txt
mymetal-1.0.9.dist-info/METADATA
mymetal-1.0.9.dist-info/WHEEL
mymetal-1.0.9.dist-info/top_level.txt
mymetal-1.0.9.dist-info/RECORD
