Metadata-Version: 2.1
Name: mymetal
Version: 1.0.9
Summary: MeBiPred
Home-page: UNKNOWN
Author: Ariel Aptekmann
Author-email: <arielaptekmann@gmail.com>
License: UNKNOWN
Keywords: python,metal binding prediction package
Platform: UNKNOWN
Classifier: Development Status :: 3 - Alpha
Classifier: Intended Audience :: Education
Classifier: Programming Language :: Python :: 2
Classifier: Programming Language :: Python :: 3
Classifier: Operating System :: MacOS :: MacOS X
Classifier: Operating System :: Microsoft :: Windows
Requires-Dist: absl-py (>=0.11.0)
Requires-Dist: astroid (>=2.4.2)
Requires-Dist: astunparse (>=1.6.3)
Requires-Dist: biopython (>=1.78)
Requires-Dist: cached-property (>=1.5.2)
Requires-Dist: cachetools (>=4.2.1)
Requires-Dist: certifi (>=2020.12.5)
Requires-Dist: chardet (>=4.0.0)
Requires-Dist: flatbuffers (>=1.12)
Requires-Dist: gast (>=0.3.3)
Requires-Dist: google-auth (>=1.25.0)
Requires-Dist: google-auth-oauthlib (>=0.4.2)
Requires-Dist: google-pasta (>=0.2.0)
Requires-Dist: grpcio (>=1.32.0)
Requires-Dist: h5py (>=2.10.0)
Requires-Dist: idna (>=2.10)
Requires-Dist: importlib-metadata (>=3.4.0)
Requires-Dist: isort (>=5.7.0)
Requires-Dist: joblib (>=1.0.0)
Requires-Dist: Keras (>=2.4.3)
Requires-Dist: Keras-Preprocessing (>=1.1.2)
Requires-Dist: lazy-object-proxy (>=1.4.3)
Requires-Dist: Markdown (>=3.3.3)
Requires-Dist: mccabe (>=0.6.1)
Requires-Dist: numpy (>=1.19.5)
Requires-Dist: oauthlib (>=3.1.0)
Requires-Dist: opt-einsum (>=3.3.0)
Requires-Dist: progress (>=1.5)
Requires-Dist: protobuf (>=3.14.0)
Requires-Dist: pyasn1 (>=0.4.8)
Requires-Dist: pyasn1-modules (>=0.2.8)
Requires-Dist: pylint (>=2.6.0)
Requires-Dist: PyYAML
Requires-Dist: requests (>=2.25.1)
Requires-Dist: requests-oauthlib (>=1.3.0)
Requires-Dist: rsa (>=4.7)
Requires-Dist: scikit-learn (>=0.24.1)
Requires-Dist: scipy (>=1.6.0)
Requires-Dist: six (>=1.15.0)
Requires-Dist: sklearn
Requires-Dist: tensorboard (>=2.4.1)
Requires-Dist: tensorboard-plugin-wit (>=1.8.0)
Requires-Dist: tensorflow (>=2.4.1)
Requires-Dist: tensorflow-estimator (>=2.4.0)
Requires-Dist: termcolor (>=1.1.0)
Requires-Dist: threadpoolctl (>=2.1.0)
Requires-Dist: toml (>=0.10.2)
Requires-Dist: typed-ast (>=1.4.2)
Requires-Dist: typing-extensions (>=3.7.4.3)
Requires-Dist: urllib3 (>=1.26.3)
Requires-Dist: Werkzeug (>=1.0.1)
Requires-Dist: wrapt (>=1.12.1)
Requires-Dist: zipp (>=3.4.0)
